nrgpy/__init__.py
nrgpy/api/__init__.py
nrgpy/api/auth.py
nrgpy/api/catalog.py
nrgpy/api/convert.py
nrgpy/api/export.py
nrgpy/api/upload.py
nrgpy/cloud_api/__init__.py
nrgpy/cloud_api/auth.py
nrgpy/cloud_api/convert.py
nrgpy/cloud_api/export.py
nrgpy/cloud_api/jobs.py
nrgpy/cloud_api/sites.py
nrgpy/cloud_api/upload.py
nrgpy/common/__init__.py
nrgpy/common/enums.py
nrgpy/common/log.py
nrgpy/convert/__init__.py
nrgpy/convert/convert_rld.py
nrgpy/convert/convert_rwd.py
nrgpy/quality/__init__.py
nrgpy/quality/quality.py
nrgpy/read/__init__.py
nrgpy/read/channel_info_arrays.py
nrgpy/read/logr.py
nrgpy/read/spidar_txt.py
nrgpy/read/sympro_txt.py
nrgpy/read/txt_utils.py
nrgpy/utils/__init__.py
nrgpy/utils/encodings.py
nrgpy/utils/ipk2lgr.py
nrgpy/utils/nsd_functions.py
nrgpy/utils/utilities.py
nrgpy-2.3.12.dist-info/licenses/LICENSE
nrgpy-2.3.12.dist-info/METADATA
nrgpy-2.3.12.dist-info/WHEEL
nrgpy-2.3.12.dist-info/top_level.txt
nrgpy-2.3.12.dist-info/RECORD
