Metadata-Version: 2.4
Name: nrgpy
Version: 2.3.12
Summary: library for handling NRG Systems data files
Author-email: David Carlson <drc@nrgsystems.com>, Natalie Babij <natalie@chickadeemail.com>, NRG Technical Services <support@nrgsystems.com>
Maintainer-email: David Carlson <davec.vt@gmail.com>
License: Copyright (c) 2023 NRG Systems, Inc.
Project-URL: Repository, https://github.com/nrgpy/nrgpy
Project-URL: Documentation, https://nrgpy.github.io/nrgpy/index.html
Keywords: nrg,nrg systems,symphonie,symphonieplus,symphonieplus3,symphoniepro,logr,data,wind,solar,remote sensor,rsd,lidar,spidar
Classifier: License :: OSI Approved :: MIT License
Classifier: Natural Language :: English
Classifier: Operating System :: OS Independent
Classifier: Programming Language :: Python :: 3
Classifier: Programming Language :: Python :: 3.8
Classifier: Programming Language :: Python :: 3.9
Classifier: Programming Language :: Python :: 3.10
Classifier: Programming Language :: Python :: 3.11
Classifier: Programming Language :: Python :: 3.12
Requires-Python: >=3.8
License-File: LICENSE
Requires-Dist: packaging
Requires-Dist: pandas>=1.5,>=2.0
Requires-Dist: psutil
Requires-Dist: requests
Provides-Extra: test
Requires-Dist: pytest; extra == "test"
Provides-Extra: dev
Requires-Dist: ruff; extra == "dev"
Requires-Dist: black; extra == "dev"
Requires-Dist: jupyterlab; extra == "dev"
Provides-Extra: docs
Requires-Dist: numpydoc; extra == "docs"
Requires-Dist: sphinx; extra == "docs"
Requires-Dist: sphinx-book-theme; extra == "docs"
Dynamic: license-file
